README.md
setup.py
currency_converter/__init__.py
python_rt_currency_converter.egg-info/PKG-INFO
python_rt_currency_converter.egg-info/SOURCES.txt
python_rt_currency_converter.egg-info/dependency_links.txt
python_rt_currency_converter.egg-info/not-zip-safe
python_rt_currency_converter.egg-info/requires.txt
python_rt_currency_converter.egg-info/top_level.txt