Metadata-Version: 1.0
Name: python-rt-currency-converter
Version: 0.0.2
Summary: Python real time rates currency converter
Home-page: https://github.com/remaudcorentin-dev/python-rt-currency-converter
Author: Corentin Remaud
Author-email: remaudcorentin.dev@gmail.com
License: MIT
Platform: UNKNOWN
